{
  "timestamp": "2025-09-15T21:16:05.325033+00:00",
  "total_recent_forks": 5,
  "recent_forks": [
    {
      "id": 1057498470,
      "node_id": "R_kgDOPwglZg",
      "name": "ManifestHub",
      "full_name": "jukmisael/ManifestHub",
      "private": false,
      "owner": {
        "login": "jukmisael",
        "id": 29514061,
        "node_id": "MDQ6VXNlcjI5NTE0MDYx",
        "avatar_url": "https://avatars.githubusercontent.com/u/29514061?v=4",
        "gravatar_id": "",
        "url": "https://api.github.com/users/jukmisael",
        "html_url": "https://github.com/jukmisael",
        "followers_url": "https://api.github.com/users/jukmisael/followers",
        "following_url": "https://api.github.com/users/jukmisael/following{/other_user}",
        "gists_url": "https://api.github.com/users/jukmisael/gists{/gist_id}",
        "starred_url": "https://api.github.com/users/jukmisael/starred{/owner}{/repo}",
        "subscriptions_url": "https://api.github.com/users/jukmisael/subscriptions",
        "organizations_url": "https://api.github.com/users/jukmisael/orgs",
        "repos_url": "https://api.github.com/users/jukmisael/repos",
        "events_url": "https://api.github.com/users/jukmisael/events{/privacy}",
        "received_events_url": "https://api.github.com/users/jukmisael/received_events",
        "type": "User",
        "user_view_type": "public",
        "site_admin": false
      },
      "html_url": "https://github.com/jukmisael/ManifestHub",
      "description": "Steam Depot Manifest Library",
      "fork": true,
      "url": "https://api.github.com/repos/jukmisael/ManifestHub",
      "forks_url": "https://api.github.com/repos/jukmisael/ManifestHub/forks",
      "keys_url": "https://api.github.com/repos/jukmisael/ManifestHub/keys{/key_id}",
      "collaborators_url": "https://api.github.com/repos/jukmisael/ManifestHub/collaborators{/collaborator}",
      "teams_url": "https://api.github.com/repos/jukmisael/ManifestHub/teams",
      "hooks_url": "https://api.github.com/repos/jukmisael/ManifestHub/hooks",
      "issue_events_url": "https://api.github.com/repos/jukmisael/ManifestHub/issues/events{/number}",
      "events_url": "https://api.github.com/repos/jukmisael/ManifestHub/events",
      "assignees_url": "https://api.github.com/repos/jukmisael/ManifestHub/assignees{/user}",
      "branches_url": "https://api.github.com/repos/jukmisael/ManifestHub/branches{/branch}",
      "tags_url": "https://api.github.com/repos/jukmisael/ManifestHub/tags",
      "blobs_url": "https://api.github.com/repos/jukmisael/ManifestHub/git/blobs{/sha}",
      "git_tags_url": "https://api.github.com/repos/jukmisael/ManifestHub/git/tags{/sha}",
      "git_refs_url": "https://api.github.com/repos/jukmisael/ManifestHub/git/refs{/sha}",
      "trees_url": "https://api.github.com/repos/jukmisael/ManifestHub/git/trees{/sha}",
      "statuses_url": "https://api.github.com/repos/jukmisael/ManifestHub/statuses/{sha}",
      "languages_url": "https://api.github.com/repos/jukmisael/ManifestHub/languages",
      "stargazers_url": "https://api.github.com/repos/jukmisael/ManifestHub/stargazers",
      "contributors_url": "https://api.github.com/repos/jukmisael/ManifestHub/contributors",
      "subscribers_url": "https://api.github.com/repos/jukmisael/ManifestHub/subscribers",
      "subscription_url": "https://api.github.com/repos/jukmisael/ManifestHub/subscription",
      "commits_url": "https://api.github.com/repos/jukmisael/ManifestHub/commits{/sha}",
      "git_commits_url": "https://api.github.com/repos/jukmisael/ManifestHub/git/commits{/sha}",
      "comments_url": "https://api.github.com/repos/jukmisael/ManifestHub/comments{/number}",
      "issue_comment_url": "https://api.github.com/repos/jukmisael/ManifestHub/issues/comments{/number}",
      "contents_url": "https://api.github.com/repos/jukmisael/ManifestHub/contents/{+path}",
      "compare_url": "https://api.github.com/repos/jukmisael/ManifestHub/compare/{base}...{head}",
      "merges_url": "https://api.github.com/repos/jukmisael/ManifestHub/merges",
      "archive_url": "https://api.github.com/repos/jukmisael/ManifestHub/{archive_format}{/ref}",
      "downloads_url": "https://api.github.com/repos/jukmisael/ManifestHub/downloads",
      "issues_url": "https://api.github.com/repos/jukmisael/ManifestHub/issues{/number}",
      "pulls_url": "https://api.github.com/repos/jukmisael/ManifestHub/pulls{/number}",
      "milestones_url": "https://api.github.com/repos/jukmisael/ManifestHub/milestones{/number}",
      "notifications_url": "https://api.github.com/repos/jukmisael/ManifestHub/notifications{?since,all,participating}",
      "labels_url": "https://api.github.com/repos/jukmisael/ManifestHub/labels{/name}",
      "releases_url": "https://api.github.com/repos/jukmisael/ManifestHub/releases{/id}",
      "deployments_url": "https://api.github.com/repos/jukmisael/ManifestHub/deployments",
      "created_at": "2025-09-15T20:09:59Z",
      "updated_at": "2025-09-15T21:14:39Z",
      "pushed_at": "2025-09-15T21:15:36Z",
      "git_url": "git://github.com/jukmisael/ManifestHub.git",
      "ssh_url": "git@github.com:jukmisael/ManifestHub.git",
      "clone_url": "https://github.com/jukmisael/ManifestHub.git",
      "svn_url": "https://github.com/jukmisael/ManifestHub",
      "homepage": null,
      "size": 21494726,
      "stargazers_count": 0,
      "watchers_count": 0,
      "language": "Python",
      "has_issues": false,
      "has_projects": true,
      "has_downloads": true,
      "has_wiki": false,
      "has_pages": false,
      "has_discussions": false,
      "forks_count": 0,
      "mirror_url": null,
      "archived": false,
      "disabled": false,
      "open_issues_count": 0,
      "license": null,
      "allow_forking": true,
      "is_template": false,
      "web_commit_signoff_required": false,
      "topics": [],
      "visibility": "public",
      "forks": 0,
      "open_issues": 0,
      "watchers": 0,
      "default_branch": "main",
      "permissions": {
        "admin": false,
        "maintain": false,
        "push": false,
        "triage": false,
        "pull": false
      }
    },
    {
      "id": 1003109816,
      "node_id": "R_kgDOO8o9uA",
      "name": "SB_manifest_DB",
      "full_name": "SPIN0ZAi/SB_manifest_DB",
      "private": false,
      "owner": {
        "login": "SPIN0ZAi",
        "id": 109903730,
        "node_id": "U_kgDOBoz_cg",
        "avatar_url": "https://avatars.githubusercontent.com/u/109903730?v=4",
        "gravatar_id": "",
        "url": "https://api.github.com/users/SPIN0ZAi",
        "html_url": "https://github.com/SPIN0ZAi",
        "followers_url": "https://api.github.com/users/SPIN0ZAi/followers",
        "following_url": "https://api.github.com/users/SPIN0ZAi/following{/other_user}",
        "gists_url": "https://api.github.com/users/SPIN0ZAi/gists{/gist_id}",
        "starred_url": "https://api.github.com/users/SPIN0ZAi/starred{/owner}{/repo}",
        "subscriptions_url": "https://api.github.com/users/SPIN0ZAi/subscriptions",
        "organizations_url": "https://api.github.com/users/SPIN0ZAi/orgs",
        "repos_url": "https://api.github.com/users/SPIN0ZAi/repos",
        "events_url": "https://api.github.com/users/SPIN0ZAi/events{/privacy}",
        "received_events_url": "https://api.github.com/users/SPIN0ZAi/received_events",
        "type": "User",
        "user_view_type": "public",
        "site_admin": false
      },
      "html_url": "https://github.com/SPIN0ZAi/SB_manifest_DB",
      "description": "Steam Depot Manifest Library",
      "fork": true,
      "url": "https://api.github.com/repos/SPIN0ZAi/SB_manifest_DB",
      "forks_url": "https://api.github.com/repos/SPIN0ZAi/SB_manifest_DB/forks",
      "keys_url": "https://api.github.com/repos/SPIN0ZAi/SB_manifest_DB/keys{/key_id}",
      "collaborators_url": "https://api.github.com/repos/SPIN0ZAi/SB_manifest_DB/collaborators{/collaborator}",
      "teams_url": "https://api.github.com/repos/SPIN0ZAi/SB_manifest_DB/teams",
      "hooks_url": "https://api.github.com/repos/SPIN0ZAi/SB_manifest_DB/hooks",
      "issue_events_url": "https://api.github.com/repos/SPIN0ZAi/SB_manifest_DB/issues/events{/number}",
      "events_url": "https://api.github.com/repos/SPIN0ZAi/SB_manifest_DB/events",
      "assignees_url": "https://api.github.com/repos/SPIN0ZAi/SB_manifest_DB/assignees{/user}",
      "branches_url": "https://api.github.com/repos/SPIN0ZAi/SB_manifest_DB/branches{/branch}",
      "tags_url": "https://api.github.com/repos/SPIN0ZAi/SB_manifest_DB/tags",
      "blobs_url": "https://api.github.com/repos/SPIN0ZAi/SB_manifest_DB/git/blobs{/sha}",
      "git_tags_url": "https://api.github.com/repos/SPIN0ZAi/SB_manifest_DB/git/tags{/sha}",
      "git_refs_url": "https://api.github.com/repos/SPIN0ZAi/SB_manifest_DB/git/refs{/sha}",
      "trees_url": "https://api.github.com/repos/SPIN0ZAi/SB_manifest_DB/git/trees{/sha}",
      "statuses_url": "https://api.github.com/repos/SPIN0ZAi/SB_manifest_DB/statuses/{sha}",
      "languages_url": "https://api.github.com/repos/SPIN0ZAi/SB_manifest_DB/languages",
      "stargazers_url": "https://api.github.com/repos/SPIN0ZAi/SB_manifest_DB/stargazers",
      "contributors_url": "https://api.github.com/repos/SPIN0ZAi/SB_manifest_DB/contributors",
      "subscribers_url": "https://api.github.com/repos/SPIN0ZAi/SB_manifest_DB/subscribers",
      "subscription_url": "https://api.github.com/repos/SPIN0ZAi/SB_manifest_DB/subscription",
      "commits_url": "https://api.github.com/repos/SPIN0ZAi/SB_manifest_DB/commits{/sha}",
      "git_commits_url": "https://api.github.com/repos/SPIN0ZAi/SB_manifest_DB/git/commits{/sha}",
      "comments_url": "https://api.github.com/repos/SPIN0ZAi/SB_manifest_DB/comments{/number}",
      "issue_comment_url": "https://api.github.com/repos/SPIN0ZAi/SB_manifest_DB/issues/comments{/number}",
      "contents_url": "https://api.github.com/repos/SPIN0ZAi/SB_manifest_DB/contents/{+path}",
      "compare_url": "https://api.github.com/repos/SPIN0ZAi/SB_manifest_DB/compare/{base}...{head}",
      "merges_url": "https://api.github.com/repos/SPIN0ZAi/SB_manifest_DB/merges",
      "archive_url": "https://api.github.com/repos/SPIN0ZAi/SB_manifest_DB/{archive_format}{/ref}",
      "downloads_url": "https://api.github.com/repos/SPIN0ZAi/SB_manifest_DB/downloads",
      "issues_url": "https://api.github.com/repos/SPIN0ZAi/SB_manifest_DB/issues{/number}",
      "pulls_url": "https://api.github.com/repos/SPIN0ZAi/SB_manifest_DB/pulls{/number}",
      "milestones_url": "https://api.github.com/repos/SPIN0ZAi/SB_manifest_DB/milestones{/number}",
      "notifications_url": "https://api.github.com/repos/SPIN0ZAi/SB_manifest_DB/notifications{?since,all,participating}",
      "labels_url": "https://api.github.com/repos/SPIN0ZAi/SB_manifest_DB/labels{/name}",
      "releases_url": "https://api.github.com/repos/SPIN0ZAi/SB_manifest_DB/releases{/id}",
      "deployments_url": "https://api.github.com/repos/SPIN0ZAi/SB_manifest_DB/deployments",
      "created_at": "2025-06-16T16:29:29Z",
      "updated_at": "2025-08-02T01:16:13Z",
      "pushed_at": "2025-09-15T20:01:12Z",
      "git_url": "git://github.com/SPIN0ZAi/SB_manifest_DB.git",
      "ssh_url": "git@github.com:SPIN0ZAi/SB_manifest_DB.git",
      "clone_url": "https://github.com/SPIN0ZAi/SB_manifest_DB.git",
      "svn_url": "https://github.com/SPIN0ZAi/SB_manifest_DB",
      "homepage": null,
      "size": 21115701,
      "stargazers_count": 1,
      "watchers_count": 1,
      "language": null,
      "has_issues": false,
      "has_projects": true,
      "has_downloads": true,
      "has_wiki": false,
      "has_pages": false,
      "has_discussions": false,
      "forks_count": 0,
      "mirror_url": null,
      "archived": false,
      "disabled": false,
      "open_issues_count": 0,
      "license": null,
      "allow_forking": true,
      "is_template": false,
      "web_commit_signoff_required": false,
      "topics": [],
      "visibility": "public",
      "forks": 0,
      "open_issues": 0,
      "watchers": 1,
      "default_branch": "main",
      "permissions": {
        "admin": false,
        "maintain": false,
        "push": false,
        "triage": false,
        "pull": false
      }
    },
    {
      "id": 968179953,
      "node_id": "R_kgDOObVA8Q",
      "name": "sojogames",
      "full_name": "sojorepo/sojogames",
      "private": false,
      "owner": {
        "login": "sojorepo",
        "id": 207276940,
        "node_id": "U_kgDODFrLjA",
        "avatar_url": "https://avatars.githubusercontent.com/u/207276940?v=4",
        "gravatar_id": "",
        "url": "https://api.github.com/users/sojorepo",
        "html_url": "https://github.com/sojorepo",
        "followers_url": "https://api.github.com/users/sojorepo/followers",
        "following_url": "https://api.github.com/users/sojorepo/following{/other_user}",
        "gists_url": "https://api.github.com/users/sojorepo/gists{/gist_id}",
        "starred_url": "https://api.github.com/users/sojorepo/starred{/owner}{/repo}",
        "subscriptions_url": "https://api.github.com/users/sojorepo/subscriptions",
        "organizations_url": "https://api.github.com/users/sojorepo/orgs",
        "repos_url": "https://api.github.com/users/sojorepo/repos",
        "events_url": "https://api.github.com/users/sojorepo/events{/privacy}",
        "received_events_url": "https://api.github.com/users/sojorepo/received_events",
        "type": "User",
        "user_view_type": "public",
        "site_admin": false
      },
      "html_url": "https://github.com/sojorepo/sojogames",
      "description": "Steam Depot Manifest Library",
      "fork": true,
      "url": "https://api.github.com/repos/sojorepo/sojogames",
      "forks_url": "https://api.github.com/repos/sojorepo/sojogames/forks",
      "keys_url": "https://api.github.com/repos/sojorepo/sojogames/keys{/key_id}",
      "collaborators_url": "https://api.github.com/repos/sojorepo/sojogames/collaborators{/collaborator}",
      "teams_url": "https://api.github.com/repos/sojorepo/sojogames/teams",
      "hooks_url": "https://api.github.com/repos/sojorepo/sojogames/hooks",
      "issue_events_url": "https://api.github.com/repos/sojorepo/sojogames/issues/events{/number}",
      "events_url": "https://api.github.com/repos/sojorepo/sojogames/events",
      "assignees_url": "https://api.github.com/repos/sojorepo/sojogames/assignees{/user}",
      "branches_url": "https://api.github.com/repos/sojorepo/sojogames/branches{/branch}",
      "tags_url": "https://api.github.com/repos/sojorepo/sojogames/tags",
      "blobs_url": "https://api.github.com/repos/sojorepo/sojogames/git/blobs{/sha}",
      "git_tags_url": "https://api.github.com/repos/sojorepo/sojogames/git/tags{/sha}",
      "git_refs_url": "https://api.github.com/repos/sojorepo/sojogames/git/refs{/sha}",
      "trees_url": "https://api.github.com/repos/sojorepo/sojogames/git/trees{/sha}",
      "statuses_url": "https://api.github.com/repos/sojorepo/sojogames/statuses/{sha}",
      "languages_url": "https://api.github.com/repos/sojorepo/sojogames/languages",
      "stargazers_url": "https://api.github.com/repos/sojorepo/sojogames/stargazers",
      "contributors_url": "https://api.github.com/repos/sojorepo/sojogames/contributors",
      "subscribers_url": "https://api.github.com/repos/sojorepo/sojogames/subscribers",
      "subscription_url": "https://api.github.com/repos/sojorepo/sojogames/subscription",
      "commits_url": "https://api.github.com/repos/sojorepo/sojogames/commits{/sha}",
      "git_commits_url": "https://api.github.com/repos/sojorepo/sojogames/git/commits{/sha}",
      "comments_url": "https://api.github.com/repos/sojorepo/sojogames/comments{/number}",
      "issue_comment_url": "https://api.github.com/repos/sojorepo/sojogames/issues/comments{/number}",
      "contents_url": "https://api.github.com/repos/sojorepo/sojogames/contents/{+path}",
      "compare_url": "https://api.github.com/repos/sojorepo/sojogames/compare/{base}...{head}",
      "merges_url": "https://api.github.com/repos/sojorepo/sojogames/merges",
      "archive_url": "https://api.github.com/repos/sojorepo/sojogames/{archive_format}{/ref}",
      "downloads_url": "https://api.github.com/repos/sojorepo/sojogames/downloads",
      "issues_url": "https://api.github.com/repos/sojorepo/sojogames/issues{/number}",
      "pulls_url": "https://api.github.com/repos/sojorepo/sojogames/pulls{/number}",
      "milestones_url": "https://api.github.com/repos/sojorepo/sojogames/milestones{/number}",
      "notifications_url": "https://api.github.com/repos/sojorepo/sojogames/notifications{?since,all,participating}",
      "labels_url": "https://api.github.com/repos/sojorepo/sojogames/labels{/name}",
      "releases_url": "https://api.github.com/repos/sojorepo/sojogames/releases{/id}",
      "deployments_url": "https://api.github.com/repos/sojorepo/sojogames/deployments",
      "created_at": "2025-04-17T16:31:33Z",
      "updated_at": "2025-07-16T18:10:42Z",
      "pushed_at": "2025-09-15T07:36:12Z",
      "git_url": "git://github.com/sojorepo/sojogames.git",
      "ssh_url": "git@github.com:sojorepo/sojogames.git",
      "clone_url": "https://github.com/sojorepo/sojogames.git",
      "svn_url": "https://github.com/sojorepo/sojogames",
      "homepage": "",
      "size": 12342193,
      "stargazers_count": 0,
      "watchers_count": 0,
      "language": null,
      "has_issues": false,
      "has_projects": true,
      "has_downloads": true,
      "has_wiki": true,
      "has_pages": false,
      "has_discussions": false,
      "forks_count": 1,
      "mirror_url": null,
      "archived": false,
      "disabled": false,
      "open_issues_count": 0,
      "license": null,
      "allow_forking": true,
      "is_template": false,
      "web_commit_signoff_required": false,
      "topics": [],
      "visibility": "public",
      "forks": 1,
      "open_issues": 0,
      "watchers": 0,
      "default_branch": "main",
      "permissions": {
        "admin": false,
        "maintain": false,
        "push": false,
        "triage": false,
        "pull": false
      }
    },
    {
      "id": 990675150,
      "node_id": "R_kgDOOwyAzg",
      "name": "ManifestHub",
      "full_name": "kkrmpubg/ManifestHub",
      "private": false,
      "owner": {
        "login": "kkrmpubg",
        "id": 110752592,
        "node_id": "U_kgDOBpnzUA",
        "avatar_url": "https://avatars.githubusercontent.com/u/110752592?v=4",
        "gravatar_id": "",
        "url": "https://api.github.com/users/kkrmpubg",
        "html_url": "https://github.com/kkrmpubg",
        "followers_url": "https://api.github.com/users/kkrmpubg/followers",
        "following_url": "https://api.github.com/users/kkrmpubg/following{/other_user}",
        "gists_url": "https://api.github.com/users/kkrmpubg/gists{/gist_id}",
        "starred_url": "https://api.github.com/users/kkrmpubg/starred{/owner}{/repo}",
        "subscriptions_url": "https://api.github.com/users/kkrmpubg/subscriptions",
        "organizations_url": "https://api.github.com/users/kkrmpubg/orgs",
        "repos_url": "https://api.github.com/users/kkrmpubg/repos",
        "events_url": "https://api.github.com/users/kkrmpubg/events{/privacy}",
        "received_events_url": "https://api.github.com/users/kkrmpubg/received_events",
        "type": "User",
        "user_view_type": "public",
        "site_admin": false
      },
      "html_url": "https://github.com/kkrmpubg/ManifestHub",
      "description": "Steam Depot Manifest Library",
      "fork": true,
      "url": "https://api.github.com/repos/kkrmpubg/ManifestHub",
      "forks_url": "https://api.github.com/repos/kkrmpubg/ManifestHub/forks",
      "keys_url": "https://api.github.com/repos/kkrmpubg/ManifestHub/keys{/key_id}",
      "collaborators_url": "https://api.github.com/repos/kkrmpubg/ManifestHub/collaborators{/collaborator}",
      "teams_url": "https://api.github.com/repos/kkrmpubg/ManifestHub/teams",
      "hooks_url": "https://api.github.com/repos/kkrmpubg/ManifestHub/hooks",
      "issue_events_url": "https://api.github.com/repos/kkrmpubg/ManifestHub/issues/events{/number}",
      "events_url": "https://api.github.com/repos/kkrmpubg/ManifestHub/events",
      "assignees_url": "https://api.github.com/repos/kkrmpubg/ManifestHub/assignees{/user}",
      "branches_url": "https://api.github.com/repos/kkrmpubg/ManifestHub/branches{/branch}",
      "tags_url": "https://api.github.com/repos/kkrmpubg/ManifestHub/tags",
      "blobs_url": "https://api.github.com/repos/kkrmpubg/ManifestHub/git/blobs{/sha}",
      "git_tags_url": "https://api.github.com/repos/kkrmpubg/ManifestHub/git/tags{/sha}",
      "git_refs_url": "https://api.github.com/repos/kkrmpubg/ManifestHub/git/refs{/sha}",
      "trees_url": "https://api.github.com/repos/kkrmpubg/ManifestHub/git/trees{/sha}",
      "statuses_url": "https://api.github.com/repos/kkrmpubg/ManifestHub/statuses/{sha}",
      "languages_url": "https://api.github.com/repos/kkrmpubg/ManifestHub/languages",
      "stargazers_url": "https://api.github.com/repos/kkrmpubg/ManifestHub/stargazers",
      "contributors_url": "https://api.github.com/repos/kkrmpubg/ManifestHub/contributors",
      "subscribers_url": "https://api.github.com/repos/kkrmpubg/ManifestHub/subscribers",
      "subscription_url": "https://api.github.com/repos/kkrmpubg/ManifestHub/subscription",
      "commits_url": "https://api.github.com/repos/kkrmpubg/ManifestHub/commits{/sha}",
      "git_commits_url": "https://api.github.com/repos/kkrmpubg/ManifestHub/git/commits{/sha}",
      "comments_url": "https://api.github.com/repos/kkrmpubg/ManifestHub/comments{/number}",
      "issue_comment_url": "https://api.github.com/repos/kkrmpubg/ManifestHub/issues/comments{/number}",
      "contents_url": "https://api.github.com/repos/kkrmpubg/ManifestHub/contents/{+path}",
      "compare_url": "https://api.github.com/repos/kkrmpubg/ManifestHub/compare/{base}...{head}",
      "merges_url": "https://api.github.com/repos/kkrmpubg/ManifestHub/merges",
      "archive_url": "https://api.github.com/repos/kkrmpubg/ManifestHub/{archive_format}{/ref}",
      "downloads_url": "https://api.github.com/repos/kkrmpubg/ManifestHub/downloads",
      "issues_url": "https://api.github.com/repos/kkrmpubg/ManifestHub/issues{/number}",
      "pulls_url": "https://api.github.com/repos/kkrmpubg/ManifestHub/pulls{/number}",
      "milestones_url": "https://api.github.com/repos/kkrmpubg/ManifestHub/milestones{/number}",
      "notifications_url": "https://api.github.com/repos/kkrmpubg/ManifestHub/notifications{?since,all,participating}",
      "labels_url": "https://api.github.com/repos/kkrmpubg/ManifestHub/labels{/name}",
      "releases_url": "https://api.github.com/repos/kkrmpubg/ManifestHub/releases{/id}",
      "deployments_url": "https://api.github.com/repos/kkrmpubg/ManifestHub/deployments",
      "created_at": "2025-05-26T13:13:58Z",
      "updated_at": "2025-05-26T14:24:37Z",
      "pushed_at": "2025-09-14T17:34:14Z",
      "git_url": "git://github.com/kkrmpubg/ManifestHub.git",
      "ssh_url": "git@github.com:kkrmpubg/ManifestHub.git",
      "clone_url": "https://github.com/kkrmpubg/ManifestHub.git",
      "svn_url": "https://github.com/kkrmpubg/ManifestHub",
      "homepage": null,
      "size": 86199,
      "stargazers_count": 0,
      "watchers_count": 0,
      "language": null,
      "has_issues": false,
      "has_projects": true,
      "has_downloads": true,
      "has_wiki": true,
      "has_pages": false,
      "has_discussions": false,
      "forks_count": 0,
      "mirror_url": null,
      "archived": false,
      "disabled": false,
      "open_issues_count": 0,
      "license": null,
      "allow_forking": true,
      "is_template": false,
      "web_commit_signoff_required": false,
      "topics": [],
      "visibility": "public",
      "forks": 0,
      "open_issues": 0,
      "watchers": 0,
      "default_branch": "main",
      "permissions": {
        "admin": false,
        "maintain": false,
        "push": false,
        "triage": false,
        "pull": false
      }
    },
    {
      "id": 979387681,
      "node_id": "R_kgDOOmBFIQ",
      "name": "ManifestHub",
      "full_name": "le31ei/ManifestHub",
      "private": false,
      "owner": {
        "login": "le31ei",
        "id": 8900532,
        "node_id": "MDQ6VXNlcjg5MDA1MzI=",
        "avatar_url": "https://avatars.githubusercontent.com/u/8900532?v=4",
        "gravatar_id": "",
        "url": "https://api.github.com/users/le31ei",
        "html_url": "https://github.com/le31ei",
        "followers_url": "https://api.github.com/users/le31ei/followers",
        "following_url": "https://api.github.com/users/le31ei/following{/other_user}",
        "gists_url": "https://api.github.com/users/le31ei/gists{/gist_id}",
        "starred_url": "https://api.github.com/users/le31ei/starred{/owner}{/repo}",
        "subscriptions_url": "https://api.github.com/users/le31ei/subscriptions",
        "organizations_url": "https://api.github.com/users/le31ei/orgs",
        "repos_url": "https://api.github.com/users/le31ei/repos",
        "events_url": "https://api.github.com/users/le31ei/events{/privacy}",
        "received_events_url": "https://api.github.com/users/le31ei/received_events",
        "type": "User",
        "user_view_type": "public",
        "site_admin": false
      },
      "html_url": "https://github.com/le31ei/ManifestHub",
      "description": "Steam Depot Manifest Library",
      "fork": true,
      "url": "https://api.github.com/repos/le31ei/ManifestHub",
      "forks_url": "https://api.github.com/repos/le31ei/ManifestHub/forks",
      "keys_url": "https://api.github.com/repos/le31ei/ManifestHub/keys{/key_id}",
      "collaborators_url": "https://api.github.com/repos/le31ei/ManifestHub/collaborators{/collaborator}",
      "teams_url": "https://api.github.com/repos/le31ei/ManifestHub/teams",
      "hooks_url": "https://api.github.com/repos/le31ei/ManifestHub/hooks",
      "issue_events_url": "https://api.github.com/repos/le31ei/ManifestHub/issues/events{/number}",
      "events_url": "https://api.github.com/repos/le31ei/ManifestHub/events",
      "assignees_url": "https://api.github.com/repos/le31ei/ManifestHub/assignees{/user}",
      "branches_url": "https://api.github.com/repos/le31ei/ManifestHub/branches{/branch}",
      "tags_url": "https://api.github.com/repos/le31ei/ManifestHub/tags",
      "blobs_url": "https://api.github.com/repos/le31ei/ManifestHub/git/blobs{/sha}",
      "git_tags_url": "https://api.github.com/repos/le31ei/ManifestHub/git/tags{/sha}",
      "git_refs_url": "https://api.github.com/repos/le31ei/ManifestHub/git/refs{/sha}",
      "trees_url": "https://api.github.com/repos/le31ei/ManifestHub/git/trees{/sha}",
      "statuses_url": "https://api.github.com/repos/le31ei/ManifestHub/statuses/{sha}",
      "languages_url": "https://api.github.com/repos/le31ei/ManifestHub/languages",
      "stargazers_url": "https://api.github.com/repos/le31ei/ManifestHub/stargazers",
      "contributors_url": "https://api.github.com/repos/le31ei/ManifestHub/contributors",
      "subscribers_url": "https://api.github.com/repos/le31ei/ManifestHub/subscribers",
      "subscription_url": "https://api.github.com/repos/le31ei/ManifestHub/subscription",
      "commits_url": "https://api.github.com/repos/le31ei/ManifestHub/commits{/sha}",
      "git_commits_url": "https://api.github.com/repos/le31ei/ManifestHub/git/commits{/sha}",
      "comments_url": "https://api.github.com/repos/le31ei/ManifestHub/comments{/number}",
      "issue_comment_url": "https://api.github.com/repos/le31ei/ManifestHub/issues/comments{/number}",
      "contents_url": "https://api.github.com/repos/le31ei/ManifestHub/contents/{+path}",
      "compare_url": "https://api.github.com/repos/le31ei/ManifestHub/compare/{base}...{head}",
      "merges_url": "https://api.github.com/repos/le31ei/ManifestHub/merges",
      "archive_url": "https://api.github.com/repos/le31ei/ManifestHub/{archive_format}{/ref}",
      "downloads_url": "https://api.github.com/repos/le31ei/ManifestHub/downloads",
      "issues_url": "https://api.github.com/repos/le31ei/ManifestHub/issues{/number}",
      "pulls_url": "https://api.github.com/repos/le31ei/ManifestHub/pulls{/number}",
      "milestones_url": "https://api.github.com/repos/le31ei/ManifestHub/milestones{/number}",
      "notifications_url": "https://api.github.com/repos/le31ei/ManifestHub/notifications{?since,all,participating}",
      "labels_url": "https://api.github.com/repos/le31ei/ManifestHub/labels{/name}",
      "releases_url": "https://api.github.com/repos/le31ei/ManifestHub/releases{/id}",
      "deployments_url": "https://api.github.com/repos/le31ei/ManifestHub/deployments",
      "created_at": "2025-05-07T12:41:32Z",
      "updated_at": "2025-09-14T13:23:28Z",
      "pushed_at": "2025-09-14T13:23:08Z",
      "git_url": "git://github.com/le31ei/ManifestHub.git",
      "ssh_url": "git@github.com:le31ei/ManifestHub.git",
      "clone_url": "https://github.com/le31ei/ManifestHub.git",
      "svn_url": "https://github.com/le31ei/ManifestHub",
      "homepage": null,
      "size": 12736730,
      "stargazers_count": 0,
      "watchers_count": 0,
      "language": null,
      "has_issues": false,
      "has_projects": true,
      "has_downloads": true,
      "has_wiki": true,
      "has_pages": false,
      "has_discussions": false,
      "forks_count": 0,
      "mirror_url": null,
      "archived": false,
      "disabled": false,
      "open_issues_count": 0,
      "license": null,
      "allow_forking": true,
      "is_template": false,
      "web_commit_signoff_required": false,
      "topics": [],
      "visibility": "public",
      "forks": 0,
      "open_issues": 0,
      "watchers": 0,
      "default_branch": "main",
      "permissions": {
        "admin": false,
        "maintain": false,
        "push": false,
        "triage": false,
        "pull": false
      }
    }
  ]
}